setup.py
statsd.py
dogstatsd_python.egg-info/PKG-INFO
dogstatsd_python.egg-info/SOURCES.txt
dogstatsd_python.egg-info/dependency_links.txt
dogstatsd_python.egg-info/top_level.txt