Metadata-Version: 1.0
Name: dogstatsd-python
Version: 0.3.0
Summary: Python bindings to Datadog's API and a user-facing command line tool.
Home-page: http://www.datadoghq.com
Author: Datadog, Inc.
Author-email: packages@datadoghq.com
License: BSD
Keywords: datadog data statsd metrics
Platform: UNKNOWN
